llog/__init__.py
llog/test.py
llog/test/my_log_admin.py
llog/test/some_parts.py
llog/test/test_root.py
llog-1.4.0.dist-info/METADATA
llog-1.4.0.dist-info/WHEEL
llog-1.4.0.dist-info/top_level.txt
llog-1.4.0.dist-info/RECORD
