Metadata-Version: 2.1
Name: llog
Version: 1.4.0
Summary: local log (a logging tool that doesn't pollute the global scope)
Home-page: https://github.co.jp/
Author: bib_inf
Author-email: contact.bibinf@gmail.com
License: CC0 v1.0
Classifier: Programming Language :: Python :: 3
Classifier: Topic :: Software Development :: Libraries
Classifier: License :: CC0 1.0 Universal (CC0 1.0) Public Domain Dedication
Requires-Dist: relpath
Requires-Dist: sout
Requires-Dist: fies (>=1.6.0)
